CHANGELOG.rst
CONTRIBUTORS.rst
LICENSE.txt
MANIFEST.in
README.rst
requirements.txt
setup.py
bin/edeposit_rest_runzeo.py
bin/edeposit_rest_webserver.py
docs/Makefile
docs/__init__.py
docs/conf.py
docs/index.rst
docs/api/rest.rst
docs/api/settings.rst
docs/api/database/cache_handler.rst
docs/api/database/database.rst
docs/api/database/status_handler.rst
docs/api/database/user_handler.rst
docs/api/structures/incomming.rst
docs/api/structures/outgoing.rst
docs/api/structures/structures.rst
docs/installation/instalace_cz.rst
src/edeposit/__init__.py
src/edeposit.amqp.rest.egg-info/PKG-INFO
src/edeposit.amqp.rest.egg-info/SOURCES.txt
src/edeposit.amqp.rest.egg-info/dependency_links.txt
src/edeposit.amqp.rest.egg-info/namespace_packages.txt
src/edeposit.amqp.rest.egg-info/not-zip-safe
src/edeposit.amqp.rest.egg-info/requires.txt
src/edeposit.amqp.rest.egg-info/top_level.txt
src/edeposit/amqp/__init__.py
src/edeposit/amqp/rest/__init__.py
src/edeposit/amqp/rest/settings.py
src/edeposit/amqp/rest/database/__init__.py
src/edeposit/amqp/rest/database/cache_handler.py
src/edeposit/amqp/rest/database/status_handler.py
src/edeposit/amqp/rest/database/user_handler.py
src/edeposit/amqp/rest/structures/__init__.py
src/edeposit/amqp/rest/structures/incomming.py
src/edeposit/amqp/rest/structures/outgoing.py
tests/conftest.py
tests/example_upload.py
tests/test_context_manager.py
tests/database/test_cache_handler.py
tests/database/test_status_handler.py
tests/database/test_user_handler.py
tests/rest/test_rest.py