Metadata-Version: 1.1
Name: edeposit.amqp.rest
Version: 0.1.0
Summary: REST API to access Edeposit website.
Home-page: https://github.com/edeposit/edeposit.amqp.rest/
Author: Edeposit team
Author-email: edeposit@email.cz
License: MIT
Platform: UNKNOWN
Classifier: Development Status :: 3 - Alpha
Classifier: Intended Audience :: Developers
Classifier: Programming Language :: Python :: 2
Classifier: Programming Language :: Python :: 2.7
Classifier: License :: OSI Approved :: MIT License
